{
  "$schema": "https://raw.githubusercontent.com/SAP-samples/btp-setup-automator/main/libs/btpsa-usecase.json",
  "services": [
    {
      "name": "transport",
      "plan": "standard",
      "category": "SERVICE",
      "targetenvironment": "kymaruntime",
      "createServiceKeys": [
        "transport-standard"
      ],
      "api_resource_uri": {
        "testapi": "/versions",
        "apiBaseUrlPathKey": "data.uri",
        "oauthurlPathkey": "data.uaa.url",
        "clientId_basicUN_PathKey": "data.uaa.clientid",
        "clientSecret_basicPW_PathKey": "data.uaa.clientsecret",
        "authMethod": "oauth",
        "APITest": "no",
        "serviceID": "SERVICE-249"
      }
    }
  ],
  "enableAPITest": true
}
